Metadata-Version: 1.0
Name: zqygis
Version: 1.8
Summary: zqygis
Home-page: https://github.com/xxx
Author: zqy
Author-email: 252238741@qq.com
License: UNKNOWN
Platform: UNKNOWN
